memobase/__init__.py
memobase/error.py
memobase/network.py
memobase/utils.py
memobase/core/__init__.py
memobase/core/async_entry.py
memobase/core/blob.py
memobase/core/entry.py
memobase/core/type.py
memobase/core/user.py
memobase/patch/__init__.py
memobase/patch/openai.py
memobase-0.0.27.dist-info/LICENSE
memobase-0.0.27.dist-info/METADATA
memobase-0.0.27.dist-info/WHEEL
memobase-0.0.27.dist-info/top_level.txt
memobase-0.0.27.dist-info/RECORD
