Metadata-Version: 2.1
Name: memobase
Version: 0.0.27
Summary: Client library of Memobase: manage user memory for your LLM applications
Home-page: https://github.com/memodb-io/memobase
Author: memobase.io
License: Apache-2.0
Classifier: Programming Language :: Python :: 3
Classifier: Programming Language :: Python :: 3.11
Classifier: Programming Language :: Python :: 3.12
Classifier: Operating System :: OS Independent
Requires-Python: >=3.11
License-File: LICENSE
Requires-Dist: pydantic
Requires-Dist: httpx
Requires-Dist: openai
